openjij-0.11.6.dist-info/RECORD
openjij-0.11.6.dist-info/WHEEL
openjij-0.11.6.dist-info/METADATA
openjij-0.11.6.dist-info/licenses/LICENSE
openjij/CMakeLists.txt
openjij/compile_config.hpp
openjij/_version.py
openjij/__init__.py
openjij/declare.hpp
openjij/cxxjij.cpython-311-darwin.so
openjij/main.cpp
openjij/variable_type.py
openjij/utils/benchmark.py
openjij/utils/decorator.py
openjij/utils/graph_utils.py
openjij/utils/cxx_cast.py
openjij/utils/__init__.py
openjij/utils/time_measure.py
openjij/utils/res_convertor.py
openjij/.dylibs/libomp.dylib
openjij/sampler/sqa_sampler.py
openjij/sampler/__init__.py
openjij/sampler/response.py
openjij/sampler/sa_sampler.py
openjij/sampler/csqa_sampler.py
openjij/sampler/base_sa_sample_hubo.py
openjij/sampler/sampler.py
openjij/model/__init__.py
openjij/model/chimera_model.py
openjij/model/model.py
openjij/model/king_graph.py
