Metadata-Version: 2.1
Name: openjij
Version: 0.11.6
Summary: Framework for the Ising model and QUBO.
Author-Email: "Jij Inc." <info@openjij.org>
License: Apache License 2.0
Classifier: License :: OSI Approved :: Apache Software License
Classifier: Intended Audience :: Science/Research
Classifier: Programming Language :: Python
Classifier: Programming Language :: Python :: 3.9
Classifier: Programming Language :: Python :: 3.10
Classifier: Programming Language :: Python :: 3.11
Classifier: Programming Language :: Python :: 3.12
Classifier: Programming Language :: Python :: 3.13
Classifier: Programming Language :: Python :: 3 :: Only
Classifier: Programming Language :: Python :: Implementation :: CPython
Classifier: Operating System :: Microsoft :: Windows
Classifier: Operating System :: POSIX
Classifier: Operating System :: Unix
Classifier: Operating System :: MacOS
Project-URL: Homepage, https://www.openjij.org
Project-URL: Source, https://github.com/Jij-Inc/OpenJij
Project-URL: Documentation, https://openjij.github.io/OpenJij
Project-URL: Reference, https://jij-inc.github.io/OpenJij-Reference-Page/
Requires-Python: <3.14,>=3.9
Requires-Dist: numpy<2.4.0,>=1.19.3
Requires-Dist: dimod<0.13.0,>=0.9.11
Requires-Dist: jij-cimod<1.8.0,>=1.7.0
